{"title":"politologia szeminariumi dolgozatok es diak","uid":5268839,"size":26673152,"categoryP":"other","categoryS":"other","magnet":"?xt=urn:btih:09ab726f812db512f20c16ee883c713f7b97991a&amp;dn=politologia+szeminariumi+dolgozatok+es+diak&amp;tr=udp%3A%2F%2Ftracker.openbittorrent.com%3A80&amp;tr=udp%3A%2F%2Fopen.demonii.com%3A1337&amp;tr=udp%3A%2F%2Ftracker.coppersurfer.tk%3A6969&amp;tr=udp%3A%2F%2Fexodus.desync.com%3A6969","seeders":0,"leechers":0,"uploader":"spirit-us","files":7,"time":1262979453,"description":"Egyetemi szeminariumi dolgozatok es Dr. Bogar Laszlo prof. eloadasainak diai. \n\nKerem a szerzoi jog tiszteletben tartasat! A szoveg hivatkozas nelkuli felhasznalasa, atemelese, lemasolasa plagiumnak minosul! Az anonimitas megorzese erdekeben az elolapokon egy kod szerepel, erre lehet hivatkozni. \n\n(All rights reserved!)","torrent":{"xt":"urn:btih:09ab726f812db512f20c16ee883c713f7b97991a","amp;dn":"politologia+szeminariumi+dolgozatok+es+diak","amp;tr":["udp%3A%2F%2Ftracker.openbittorrent.com%3A80","udp%3A%2F%2Fopen.demonii.com%3A1337","udp%3A%2F%2Ftracker.coppersurfer.tk%3A6969","udp%3A%2F%2Fexodus.desync.com%3A6969"],"infoHash":"09ab726f812db512f20c16ee883c713f7b97991a","infoHashBuffer":{"type":"Buffer","data":[9,171,114,111,129,45,181,18,242,12,22,238,136,60,113,63,123,151,153,26]},"announce":[],"urlList":[]}}