{"title":"Twilight New Moon SCR-ZMT","uid":5359766,"size":1493239808,"categoryP":"video","categoryS":"movies","magnet":"?xt=urn:btih:0a071dd99c099ae49e8f496bd66cc107ce2cbfa0&amp;dn=Twilight+New+Moon+SCR-ZMT&amp;tr=udp%3A%2F%2Ftracker.openbittorrent.com%3A80&amp;tr=udp%3A%2F%2Fopen.demonii.com%3A1337&amp;tr=udp%3A%2F%2Ftracker.coppersurfer.tk%3A6969&amp;tr=udp%3A%2F%2Fexodus.desync.com%3A6969","seeders":0,"leechers":1,"uploader":"zontey","files":2,"time":1266021874,"description":"Best iÃ‚Â´ve seen so i just passing it along!\nKeep on seeding\nA/9\nV/9","torrent":{"xt":"urn:btih:0a071dd99c099ae49e8f496bd66cc107ce2cbfa0","amp;dn":"Twilight+New+Moon+SCR-ZMT","amp;tr":["udp%3A%2F%2Ftracker.openbittorrent.com%3A80","udp%3A%2F%2Fopen.demonii.com%3A1337","udp%3A%2F%2Ftracker.coppersurfer.tk%3A6969","udp%3A%2F%2Fexodus.desync.com%3A6969"],"infoHash":"0a071dd99c099ae49e8f496bd66cc107ce2cbfa0","infoHashBuffer":{"type":"Buffer","data":[10,7,29,217,156,9,154,228,158,143,73,107,214,108,193,7,206,44,191,160]},"announce":[],"urlList":[]}}