{"title":"The Dennis Prager Show 29-Jan-10 CF mp3","uid":5318866,"size":104704805,"categoryP":"audio","categoryS":"other","magnet":"?xt=urn:btih:0ea7f16ce82814b24ce2bbd05888251065f12bb1&amp;dn=The+Dennis+Prager+Show+29-Jan-10+CF+mp3&amp;tr=udp%3A%2F%2Ftracker.openbittorrent.com%3A80&amp;tr=udp%3A%2F%2Fopen.demonii.com%3A1337&amp;tr=udp%3A%2F%2Ftracker.coppersurfer.tk%3A6969&amp;tr=udp%3A%2F%2Fexodus.desync.com%3A6969","seeders":0,"leechers":1,"uploader":"jwhitt62","files":3,"time":1264801262,"description":"The Dennis Prager Show 29-Jan-10 CF mp3\n\nEdited Internet Radio Recording\n\nShow divided into three one-hour segments","torrent":{"xt":"urn:btih:0ea7f16ce82814b24ce2bbd05888251065f12bb1","amp;dn":"The+Dennis+Prager+Show+29-Jan-10+CF+mp3","amp;tr":["udp%3A%2F%2Ftracker.openbittorrent.com%3A80","udp%3A%2F%2Fopen.demonii.com%3A1337","udp%3A%2F%2Ftracker.coppersurfer.tk%3A6969","udp%3A%2F%2Fexodus.desync.com%3A6969"],"infoHash":"0ea7f16ce82814b24ce2bbd05888251065f12bb1","infoHashBuffer":{"type":"Buffer","data":[14,167,241,108,232,40,20,178,76,226,187,208,88,136,37,16,101,241,43,177]},"announce":[],"urlList":[]}}