{"title":"Best of Mr. Vic Damone - Karaoke - Michael Rizzo DJ collection","uid":5308484,"size":77338444,"categoryP":"other","categoryS":"other","magnet":"?xt=urn:btih:3fe92605c38bd612ad4bfeb306d8be1cd36da428&amp;dn=Best+of+Mr.+Vic+Damone+-+Karaoke+-+Michael+Rizzo+DJ+collection&amp;tr=udp%3A%2F%2Ftracker.openbittorrent.com%3A80&amp;tr=udp%3A%2F%2Fopen.demonii.com%3A1337&amp;tr=udp%3A%2F%2Ftracker.coppersurfer.tk%3A6969&amp;tr=udp%3A%2F%2Fexodus.desync.com%3A6969","seeders":0,"leechers":1,"uploader":"mrizzo2","files":36,"time":1264482020,"description":"Here are the songs best reflecting the career of Mr. Vic Damone\nThe &quot;stranger in Paradise rendition here is the Broadway offering \nfrom Pocket songs rather than their &quot;Judy Garland&quot; version which \nhas a varied pace from this original (although we have used that version \nbefore I must admit). Pocket songs offerings usually come in with \ngreat quality in any event. The &quot;Legends brand&quot; rendition in particular\nwas quite poor indeed we found for this particular song although they \ntoo have some great quality in their offerings too.\n\n\nOur new lineup of Karaoke will soon be available and will be revamped\nand even more comprehensive in the range of song selections, indeed!\n\nMichael Rizzo Chessman\n\nHere we are once again:\n\nArrivederci Roma wvocals\nArrivederci Roma\nGigi\nHere in my heart\nLet's Fall In Love\nMore\nMy foolish heart with (female) vocals\nMy foolish heart\nOh my wonderful one (with Italian lyrics too)\nOh My Wonderful One - Italian Wvocals\nOn The Street Where You Live\nOnce upon a time - Standard wvocals\nOnce upon a time - Standard\nSoftly as I leave you\nSome Enchanted Evening\nTill there was you\nYou're breaking my heart (with Italian lyrics too)\nYounger than springtime wvocal\n\n ","torrent":{"xt":"urn:btih:3fe92605c38bd612ad4bfeb306d8be1cd36da428","amp;dn":"Best+of+Mr.+Vic+Damone+-+Karaoke+-+Michael+Rizzo+DJ+collection","amp;tr":["udp%3A%2F%2Ftracker.openbittorrent.com%3A80","udp%3A%2F%2Fopen.demonii.com%3A1337","udp%3A%2F%2Ftracker.coppersurfer.tk%3A6969","udp%3A%2F%2Fexodus.desync.com%3A6969"],"infoHash":"3fe92605c38bd612ad4bfeb306d8be1cd36da428","infoHashBuffer":{"type":"Buffer","data":[63,233,38,5,195,139,214,18,173,75,254,179,6,216,190,28,211,109,164,40]},"announce":[],"urlList":[]}}