{"title":"VA - Club World 2009.14-CD-2009-MS_[Club]","uid":5448757,"size":164124089,"categoryP":"audio","categoryS":"music","magnet":"?xt=urn:btih:44f1cc0d4efe1f74f394060376a9eb46efd05cfc&amp;dn=VA+-+Club+World+2009.14-CD-2009-MS_%5BClub%5D&amp;tr=udp%3A%2F%2Ftracker.openbittorrent.com%3A80&amp;tr=udp%3A%2F%2Fopen.demonii.com%3A1337&amp;tr=udp%3A%2F%2Ftracker.coppersurfer.tk%3A6969&amp;tr=udp%3A%2F%2Fexodus.desync.com%3A6969","seeders":0,"leechers":0,"uploader":"Club.World.Music","files":19,"time":1269107324,"description":".:.....................................................................................................:.\n ^......................................................................................................^\n |                                                                           \t\t\t\t|\n |                                                                           \t\t\t\t|\n |                                               MUSICSHARK                                  \t\t|\n |                                                                           \t\t\t\t|\n |                                             P R O U D L Y                                 \t\t|\n |                                                                           \t\t\t\t|\n |                                               GIVES YOU                                   \t\t|\n |                                                                          \t\t\t \t|\n.:.....................................................................................................:.\n ^......................................................................................................^\n |                                                                          \t\t\t \t|\n |                                                                           \t\t\t\t|\n |  Artist: ...............VA\t\t\t\t\t\t\t\t\t\t|\n |  Title: ................Club World 2009.14\t\t\t\t\t\t\t\t|\n |  Source: ...............CDA                                               \t\t\t\t|\n |  Year:   ...............2009                                              \t\t\t\t|\n |  Label:  ...............MS\t\t\t\t\t\t\t\t\t\t|\n |  Genre:  ...............Trance/Hardtrance/Techno/House/Dance/Club\t\t\t\t\t|\n |  Release date: .........2009                                              \t\t\t\t|\n |  Bitrate: ..............128kbps\t\t                                              \t\t|\n |  Included: .............NFO, SFV, M3U                                     \t\t\t\t|\n |  Covers: ...............Front/Back                                                \t\t\t|\n |  Discs: ................01                                                \t\t\t\t|\n |  Ripped by: ............MS                                           \t\t\t\t|\n |                                                                           \t\t\t\t|\n |                                            OFFICIAL SITE:                              \t\t|\n |                                                                           \t\t\t\t|\n |                                                                      \t\t|\n |                                                                           \t\t\t\t|\n.:.....................................................................................................:.\n ^......................................................................................................^\n |                                                                           \t\t\t\t|\n |                            T R A C K  L I S T                             \t\t\t\t|\n |                  .......................................                  \t\t\t\t|\n |                                                                           \t\t\t\t|\n | 01. Karanda - Karanda (Astuni &amp; Manuel Le Saux Remix) (7:09)\t\t\t\t\t\t|\n | 02. Ma Bra - Into the Sky (Ma Bra RMX) (3:18)\t\t\t\t\t\t\t|\n | 03. Doc Phatt - Heart Of Asia (Dj Klubbingman vs. Andre Picar Booty RMX) (6:42)\t\t\t|\n | 04. Dj Seleco feat. Torny - I Love You (Kevin Dee! Remix) (3:02)\t\t\t\t\t|\n | 05. E-Type - Life (Cansis RMX) (6:14)\t\t\t\t\t\t\t\t|\n | 06. Topmodelz - Strings of Infinity 2009 (Raindropz RMX) (4:56)\t\t\t\t\t|\n | 07. Tune Up! - Another Day (Flashtunez RMX) (4:28)\t\t\t\t\t\t\t|\n | 08. Rikah - Day After Day (Oscar Salguero Club Mix) (6:57)\t\t\t\t\t\t|\n | 09. Signum - Addicted (Original Mix) (8:56)\t\t\t\t\t\t\t\t|\n | 10. Al Bizzare &amp; Babyschool - New Day (Original Mix) (5:05)\t\t\t\t\t\t|\n | 11. Linkin Park - New Divide (Topless RMX) (5:06)\t\t\t\t\t\t\t|\n | 12. ATB feat. Aruna - My Saving Grace 2009 (Orginal Mix) (4:09)\t\t\t\t\t|\n | 13. Zhi-Vago - Celebrate the Love (Van Date RMX) (7:26)\t\t\t\t\t\t|\n | 14. Clubhunter - Do Me (Dj Hyo Radio Edit) (3:22)\t\t\t\t\t\t\t|\n |\t\t\t\t\t\t\t\t\t\t\t\t\t|\n | Playing Time.........: 76:50\t\t\t\t\t\t\t\t\t\t|\n | Total Size...........: 155mb \t\t\t\t\t\t\t\t\t|\n |                                                                           \t\t\t\t|\n.:......................................................................................................:.\n ^......................................................................................................^\n |                                                                           \t\t\t\t|\n |                                              N O T E S                                   \t\t|\n |                                 .......................................                  \t\t|\n |                                                                           \t\t\t\t|\n |                                         QUALITY IS PRIDE                               \t\t|\n |                                                                           \t\t\t\t|\n | This is a new series of albums containing music in the genre of Trance, Dance, House, Techno,\t|\n | Hardtrance, Rave etc.\t\t\t\t\t\t\t\t\t\t|\n |\t\t\t\t\t\t\t\t\t\t\t\t\t|\n | Sorry about the not so good quality on some of the tracks, but the reason why it is so is because\t|\n | these track are even not released, demos, just released, promos, rare and so on. So keep that in\t|\n | mind when listening to this album. Stay tuned for other releases from us in this series.....\t\t|\n |                                                                           \t\t\t\t|\n.:......................................................................................................:.\n ^......................................................................................................^\n |                                                                           \t\t\t\t|\n |                                                                           \t\t\t\t|\n |                                                                           \t\t\t\t|\n |                                  NFO CREATED IN 2007 - BY - MUSICSHARK -                   \t\t|\n |                                                                           \t\t\t\t|\n |                                                                           \t\t\t\t|\n.:......................................................................................................:.\n ^......................................................................................................^","torrent":{"xt":"urn:btih:44f1cc0d4efe1f74f394060376a9eb46efd05cfc","amp;dn":"VA+-+Club+World+2009.14-CD-2009-MS_%5BClub%5D","amp;tr":["udp%3A%2F%2Ftracker.openbittorrent.com%3A80","udp%3A%2F%2Fopen.demonii.com%3A1337","udp%3A%2F%2Ftracker.coppersurfer.tk%3A6969","udp%3A%2F%2Fexodus.desync.com%3A6969"],"infoHash":"44f1cc0d4efe1f74f394060376a9eb46efd05cfc","infoHashBuffer":{"type":"Buffer","data":[68,241,204,13,78,254,31,116,243,148,6,3,118,169,235,70,239,208,92,252]},"announce":[],"urlList":[]}}