{"title":"Distiguished Racing History of PORSCHE","uid":5403606,"size":4291133440,"categoryP":"video","categoryS":"movies","magnet":"?xt=urn:btih:511b8116c3f2c3c6836abc92ae64bd37d90b9f75&amp;dn=Distiguished+Racing+History+of+PORSCHE&amp;tr=udp%3A%2F%2Ftracker.openbittorrent.com%3A80&amp;tr=udp%3A%2F%2Fopen.demonii.com%3A1337&amp;tr=udp%3A%2F%2Ftracker.coppersurfer.tk%3A6969&amp;tr=udp%3A%2F%2Fexodus.desync.com%3A6969","seeders":0,"leechers":2,"uploader":"PorscheSpeedster","files":1,"time":1267515604,"description":"THE DISTINGUISHED RACING HERITAGE OF PORSCHE\n\nthe triple freatures of this DVD take a close look at the PORSCHEs that have made the name an icon in automobile history.  Rare racing footage, interviews\nand close-up looks at one-of-a-kind cars make this collectors set a must see and own.\n\nThe first program features the 917 PORSCHE race cars in their 12 cylinder form.\n\nThe second; PORSCHE 930 Turbo.  A detailed look at the 76 thru 79 version of the most sought after PORSCHE.\n\nThe third program is &quot;PORSCHE A LeMANS Retrospect&quot;. This is a gathering of every factory PORSCHE race car ever produced at the Laguna Sece Raceway in \nCalifornia.","torrent":{"xt":"urn:btih:511b8116c3f2c3c6836abc92ae64bd37d90b9f75","amp;dn":"Distiguished+Racing+History+of+PORSCHE","amp;tr":["udp%3A%2F%2Ftracker.openbittorrent.com%3A80","udp%3A%2F%2Fopen.demonii.com%3A1337","udp%3A%2F%2Ftracker.coppersurfer.tk%3A6969","udp%3A%2F%2Fexodus.desync.com%3A6969"],"infoHash":"511b8116c3f2c3c6836abc92ae64bd37d90b9f75","infoHashBuffer":{"type":"Buffer","data":[81,27,129,22,195,242,195,198,131,106,188,146,174,100,189,55,217,11,159,117]},"announce":[],"urlList":[]}}