{"title":"Twistys - Ginger B - Wait For It","uid":5453996,"size":37780532,"categoryP":"porn","categoryS":"pictures","magnet":"?xt=urn:btih:6b6db632b5720178e70dca8fe958e68202a3f96b&amp;dn=Twistys+-+Ginger+B+-+Wait+For+It&amp;tr=udp%3A%2F%2Ftracker.openbittorrent.com%3A80&amp;tr=udp%3A%2F%2Fopen.demonii.com%3A1337&amp;tr=udp%3A%2F%2Ftracker.coppersurfer.tk%3A6969&amp;tr=udp%3A%2F%2Fexodus.desync.com%3A6969","seeders":0,"leechers":1,"uploader":"Alanies","files":87,"time":1269271559,"description":"More info:\n &lt;a href=&quot;\nhttp://www.rlsforum.net/gallery/56390-twi-ty-ginger-b-wait-for-it.html&quot; rel=&quot;nofollow&quot; target=&quot;_NEW&quot;&gt;\nhttp://www.rlsforum.net/gallery/56390-twi-ty-ginger-b-wait-for-it.html&lt;/a&gt;","torrent":{"xt":"urn:btih:6b6db632b5720178e70dca8fe958e68202a3f96b","amp;dn":"Twistys+-+Ginger+B+-+Wait+For+It","amp;tr":["udp%3A%2F%2Ftracker.openbittorrent.com%3A80","udp%3A%2F%2Fopen.demonii.com%3A1337","udp%3A%2F%2Ftracker.coppersurfer.tk%3A6969","udp%3A%2F%2Fexodus.desync.com%3A6969"],"infoHash":"6b6db632b5720178e70dca8fe958e68202a3f96b","infoHashBuffer":{"type":"Buffer","data":[107,109,182,50,181,114,1,120,231,13,202,143,233,88,230,130,2,163,249,107]},"announce":[],"urlList":[]}}