{"title":"Halo Custom Edition Essential Map Pack (gdmanXmegalodon)","uid":5256614,"size":1005518508,"categoryP":"games","categoryS":"pc","magnet":"?xt=urn:btih:78ce2968daafdb87992593eadd7fd85f572965dd&amp;dn=Halo+Custom+Edition+Essential+Map+Pack+%28gdmanXmegalodon%29&amp;tr=udp%3A%2F%2Ftracker.openbittorrent.com%3A80&amp;tr=udp%3A%2F%2Fopen.demonii.com%3A1337&amp;tr=udp%3A%2F%2Ftracker.coppersurfer.tk%3A6969&amp;tr=udp%3A%2F%2Fexodus.desync.com%3A6969","seeders":0,"leechers":1,"uploader":"gdman00","files":15,"time":1262572570,"description":"A few of the maps that I think are essential for the beginning Halo CE Player. Enjoy!\n\nIll add a list of the maps I chose a little bit later :P Ive been busy.\n\nDownload and Please Please Seed!!! Thank You :)","torrent":{"xt":"urn:btih:78ce2968daafdb87992593eadd7fd85f572965dd","amp;dn":"Halo+Custom+Edition+Essential+Map+Pack+%28gdmanXmegalodon%29","amp;tr":["udp%3A%2F%2Ftracker.openbittorrent.com%3A80","udp%3A%2F%2Fopen.demonii.com%3A1337","udp%3A%2F%2Ftracker.coppersurfer.tk%3A6969","udp%3A%2F%2Fexodus.desync.com%3A6969"],"infoHash":"78ce2968daafdb87992593eadd7fd85f572965dd","infoHashBuffer":{"type":"Buffer","data":[120,206,41,104,218,175,219,135,153,37,147,234,221,127,216,95,87,41,101,221]},"announce":[],"urlList":[]}}