{"title":"My Friends Hot Mom  Darla Crane 14.01.10","uid":5281445,"size":450495727,"categoryP":"porn","categoryS":"movie_clips","magnet":"?xt=urn:btih:8074adde9b1e5090cd3cfe9b8a994c79e9223a59&amp;dn=My+Friends+Hot+Mom++Darla+Crane+14.01.10&amp;tr=udp%3A%2F%2Ftracker.openbittorrent.com%3A80&amp;tr=udp%3A%2F%2Fopen.demonii.com%3A1337&amp;tr=udp%3A%2F%2Ftracker.coppersurfer.tk%3A6969&amp;tr=udp%3A%2F%2Fexodus.desync.com%3A6969","seeders":0,"leechers":1,"uploader":"brego45","files":1,"time":1263564941,"description":"Screenshots\n-----------------  &lt;a href=&quot;\nhttp://desibbrg.net/imghost/show.php?img=272880_darlaanthonyhorbigimg1.jpg.html&quot; rel=&quot;nofollow&quot; target=&quot;_NEW&quot;&gt;\nhttp://desibbrg.net/imghost/show.php?img=272880_darlaanthonyhorbigimg1.jpg.html&lt;/a&gt; &lt;a href=&quot;\nhttp://desibbrg.net/imghost/show.php?img=272879_darlaanthonyhorbigimg2.jpg.html&quot; rel=&quot;nofollow&quot; target=&quot;_NEW&quot;&gt;\nhttp://desibbrg.net/imghost/show.php?img=272879_darlaanthonyhorbigimg2.jpg.html&lt;/a&gt; &lt;a href=&quot;\nhttp://desibbrg.net/imghost/show.php?img=272878_darlaanthonyhorbigimg4.jpg.html&quot; rel=&quot;nofollow&quot; target=&quot;_NEW&quot;&gt;\nhttp://desibbrg.net/imghost/show.php?img=272878_darlaanthonyhorbigimg4.jpg.html&lt;/a&gt; &lt;a href=&quot;\nhttp://desibbrg.net/imghost/show.php?img=272877_darlaanthonyhorbigimg3.jpg.html&quot; rel=&quot;nofollow&quot; target=&quot;_NEW&quot;&gt;\nhttp://desibbrg.net/imghost/show.php?img=272877_darlaanthonyhorbigimg3.jpg.html&lt;/a&gt;\n\nMy other releases\n---------------------------  &lt;a href=&quot;\nhttp://thepiratebay.se/user/brego4&quot; rel=&quot;nofollow&quot; target=&quot;_NEW&quot;&gt;\nhttp://thepiratebay.se/user/brego4&lt;/a&gt;\t","torrent":{"xt":"urn:btih:8074adde9b1e5090cd3cfe9b8a994c79e9223a59","amp;dn":"My+Friends+Hot+Mom++Darla+Crane+14.01.10","amp;tr":["udp%3A%2F%2Ftracker.openbittorrent.com%3A80","udp%3A%2F%2Fopen.demonii.com%3A1337","udp%3A%2F%2Ftracker.coppersurfer.tk%3A6969","udp%3A%2F%2Fexodus.desync.com%3A6969"],"infoHash":"8074adde9b1e5090cd3cfe9b8a994c79e9223a59","infoHashBuffer":{"type":"Buffer","data":[128,116,173,222,155,30,80,144,205,60,254,155,138,153,76,121,233,34,58,89]},"announce":[],"urlList":[]}}