{"title":"Phase-3 (Wake Up Project) (Doco)","uid":5339041,"size":793555404,"categoryP":"video","categoryS":"movies","magnet":"?xt=urn:btih:82165c2dd6b28058a4ce2e05c10e91e00c95630e&amp;dn=Phase-3+%28Wake+Up+Project%29+%28Doco%29&amp;tr=udp%3A%2F%2Ftracker.openbittorrent.com%3A80&amp;tr=udp%3A%2F%2Fopen.demonii.com%3A1337&amp;tr=udp%3A%2F%2Ftracker.coppersurfer.tk%3A6969&amp;tr=udp%3A%2F%2Fexodus.desync.com%3A6969","seeders":0,"leechers":1,"uploader":"awais82","files":-1,"time":1265408019,"description":"Another groundbreaking and riveting series from the creators of The Arrivals and The Divine Book.\n\nWith special guests, producers, composers, and collaborating directors, Phase 3 aims to set a new standard in online films. This production will (inshallah) wake up the world, and unite the people from every country, religion, culture or creed. A film by the people, for the people. And once again completely independent, with zero budget!! Nothing but hard work and talented volunteers.\n\n  ____                      _                      _   _       _\n / ___|___  _ __  ___ _ __ (_)_ __ __ _  ___ _   _| | | |_   _| |__\n| |   / _ \\| '_ \\/ __| '_ \\| | '__/ _` |/ __| | | | |_| | | | | '_ \\\n| |__| (_) | | | \\__ \\ |_) | | | | (_| | (__| |_| |  _  | |_| | |_) |\n \\____\\___/|_| |_|___/ .__/|_|_|  \\__,_|\\___|\\__, |_| |_|\\__,_|_.__/\n                     |_|                     |___/\n   ____\n  / ___|___  _ __ ___\n | |   / _ \\| '_ ` _ \\\n | |__| (_) | | | | | |\n(_)____\\___/|_| |_| |_|\n\n\nPLEASE KEEP SEEDED TO PASS ON THE MESSAGE.  PLEASE VISIT OUR SITE AND SHARE THE WORD!\nDOWNLOAD MAYBE SLOW BUT SURE! PLEASE ASSIST IN BANDWIDTH!\n\n* Don't Be Fooled Any Longer on Darwinism, Evolution, Global Warming Lies, Internationalism, etc.\n* Get The Message Out, Openly!\n","torrent":{"xt":"urn:btih:82165c2dd6b28058a4ce2e05c10e91e00c95630e","amp;dn":"Phase-3+%28Wake+Up+Project%29+%28Doco%29","amp;tr":["udp%3A%2F%2Ftracker.openbittorrent.com%3A80","udp%3A%2F%2Fopen.demonii.com%3A1337","udp%3A%2F%2Ftracker.coppersurfer.tk%3A6969","udp%3A%2F%2Fexodus.desync.com%3A6969"],"infoHash":"82165c2dd6b28058a4ce2e05c10e91e00c95630e","infoHashBuffer":{"type":"Buffer","data":[130,22,92,45,214,178,128,88,164,206,46,5,193,14,145,224,12,149,99,14]},"announce":[],"urlList":[]}}