{"title":"2012 [NDS.movieS] .dpg.SCOPE","uid":5218211,"size":399747738,"categoryP":"video","categoryS":"handheld","magnet":"?xt=urn:btih:8eb1bb2d4afcee7c6205a1138e4223ec0c81a03b&amp;dn=2012+%5BNDS.movieS%5D+.dpg.SCOPE&amp;tr=udp%3A%2F%2Ftracker.openbittorrent.com%3A80&amp;tr=udp%3A%2F%2Fopen.demonii.com%3A1337&amp;tr=udp%3A%2F%2Ftracker.coppersurfer.tk%3A6969&amp;tr=udp%3A%2F%2Fexodus.desync.com%3A6969","seeders":0,"leechers":0,"uploader":"scope1982","files":2,"time":1260825591,"description":"\n\nnDs-mPeG, usually abbreviated DPG, is a special format of MPEG-1 video specifically for playback using the homebrew Moonshell program for the Nintendo DS. The video is encoded on a computer and then transferred, along with Moonshell, to the DS for playback.\n\n\n\nDirector: Roland Emmerich\n\nWriters: Roland Emmerich &amp; Harald Kloser \n\nRelease Date: 13 November 2009 (UK) \n\nGenre: Action | Adventure | Drama | Sci-Fi | Thriller \n\nTagline: We Were Warned. \n\nPlot: An epic adventure about a global cataclysm that brings an end to the world and tells of the heroic struggle of the survivors.","torrent":{"xt":"urn:btih:8eb1bb2d4afcee7c6205a1138e4223ec0c81a03b","amp;dn":"2012+%5BNDS.movieS%5D+.dpg.SCOPE","amp;tr":["udp%3A%2F%2Ftracker.openbittorrent.com%3A80","udp%3A%2F%2Fopen.demonii.com%3A1337","udp%3A%2F%2Ftracker.coppersurfer.tk%3A6969","udp%3A%2F%2Fexodus.desync.com%3A6969"],"infoHash":"8eb1bb2d4afcee7c6205a1138e4223ec0c81a03b","infoHashBuffer":{"type":"Buffer","data":[142,177,187,45,74,252,238,124,98,5,161,19,142,66,35,236,12,129,160,59]},"announce":[],"urlList":[]}}