{"title":"V.For.Vendetta[2005]DvDrip[Eng] DAYN ORG BY JASKARAN","uid":5279175,"size":734800933,"categoryP":"video","categoryS":"movies","magnet":"?xt=urn:btih:93cdb117c0adb522f136d312ba40fe318c0133e5&amp;dn=V.For.Vendetta%5B2005%5DDvDrip%5BEng%5D+DAYN+ORG+BY+JASKARAN&amp;tr=udp%3A%2F%2Ftracker.openbittorrent.com%3A80&amp;tr=udp%3A%2F%2Fopen.demonii.com%3A1337&amp;tr=udp%3A%2F%2Ftracker.coppersurfer.tk%3A6969&amp;tr=udp%3A%2F%2Fexodus.desync.com%3A6969","seeders":0,"leechers":1,"uploader":"jaskaransahni","files":2,"time":1263488546,"description":"DVD RIP BY JASKARAN SAHNI\n\nDAYN.ORG","torrent":{"xt":"urn:btih:93cdb117c0adb522f136d312ba40fe318c0133e5","amp;dn":"V.For.Vendetta%5B2005%5DDvDrip%5BEng%5D+DAYN+ORG+BY+JASKARAN","amp;tr":["udp%3A%2F%2Ftracker.openbittorrent.com%3A80","udp%3A%2F%2Fopen.demonii.com%3A1337","udp%3A%2F%2Ftracker.coppersurfer.tk%3A6969","udp%3A%2F%2Fexodus.desync.com%3A6969"],"infoHash":"93cdb117c0adb522f136d312ba40fe318c0133e5","infoHashBuffer":{"type":"Buffer","data":[147,205,177,23,192,173,181,34,241,54,211,18,186,64,254,49,140,1,51,229]},"announce":[],"urlList":[]}}