{"title":"the.beatles.alone.and.together.1989.dvdrip.xvid.HMV","uid":5251455,"size":746842760,"categoryP":"video","categoryS":"movies","magnet":"?xt=urn:btih:a1efc3eb3018c24ec5087cad3b89cd103c7bbdd7&amp;dn=the.beatles.alone.and.together.1989.dvdrip.xvid.HMV&amp;tr=udp%3A%2F%2Ftracker.openbittorrent.com%3A80&amp;tr=udp%3A%2F%2Fopen.demonii.com%3A1337&amp;tr=udp%3A%2F%2Ftracker.coppersurfer.tk%3A6969&amp;tr=udp%3A%2F%2Fexodus.desync.com%3A6969","seeders":0,"leechers":1,"uploader":"HMVinyl","files":-1,"time":1262373608,"description":"This is an old Beatles documentary from 1989, i got it as a xmas gift, and couldn't find it anywhere online so i decided to rip it for everyone, its not that bad, filmed shortly after the death of John Lennon.","torrent":{"xt":"urn:btih:a1efc3eb3018c24ec5087cad3b89cd103c7bbdd7","amp;dn":"the.beatles.alone.and.together.1989.dvdrip.xvid.HMV","amp;tr":["udp%3A%2F%2Ftracker.openbittorrent.com%3A80","udp%3A%2F%2Fopen.demonii.com%3A1337","udp%3A%2F%2Ftracker.coppersurfer.tk%3A6969","udp%3A%2F%2Fexodus.desync.com%3A6969"],"infoHash":"a1efc3eb3018c24ec5087cad3b89cd103c7bbdd7","infoHashBuffer":{"type":"Buffer","data":[161,239,195,235,48,24,194,78,197,8,124,173,59,137,205,16,60,123,189,215]},"announce":[],"urlList":[]}}