{"title":"Blasningen.S09E06.SWEDiSH.PDTV.XviD-iCAP","uid":5385203,"size":381916235,"categoryP":"video","categoryS":"tv_shows","magnet":"?xt=urn:btih:a2fdf9cc0f0a04168009c35cc618ddf044f01e0f&amp;dn=Blasningen.S09E06.SWEDiSH.PDTV.XviD-iCAP&amp;tr=udp%3A%2F%2Ftracker.openbittorrent.com%3A80&amp;tr=udp%3A%2F%2Fopen.demonii.com%3A1337&amp;tr=udp%3A%2F%2Ftracker.coppersurfer.tk%3A6969&amp;tr=udp%3A%2F%2Fexodus.desync.com%3A6969","seeders":0,"leechers":1,"uploader":"Pride86","files":28,"time":1266868564,"description":"Enjoy Ripp by iCAP\n\n\nTitel............: BlÃƒÂ¥sningen                    \nSÃƒÂ¤ndningsdatum...: 10/02/21                      \nSprÃƒÂ¥k............: Swedish                       \nLÃƒÂ¤nk.............: http://www.tv3.se             \nKÃƒÂ¤lla............: DVB-S                         \nVideo............: XviD (2-pass)                 \nUpplÃƒÂ¶sning.......: 640x352                       \nLjud.............: MP3 (VBR)                     \nLÃƒÂ¤ngd............: 00:45:36                      \nStorlek..........: 348,19MB                      \n\nPlot: \nNÃƒÂ¤r Regina Lund hittar en viktig portfÃƒÂ¶lj som verkar tillhÃƒÂ¶ra utrikesminister \nCarl Bildt tar hon problemet pÃƒÂ¥ fullaste allvar. - Jag ville inte bara rÃƒÂ¤dda \nSverige, utan jag ville rÃƒÂ¤dda Carl Bildt, sÃƒÂ¤ger hon till RenÃƒÂ©e i studion. Vad \nskulle du gÃƒÂ¶ra om du hittade Carl Bildts portfÃƒÂ¶lj? Om han ringde och bad dig \nlÃƒÂ¤sa igenom hemliga dokument och sammanfatta dem fÃƒÂ¶r honom? Regina Lund tvekar \ninte en sekund nÃƒÂ¤r hon gÃƒÂ¶r sitt bÃƒÂ¤sta fÃƒÂ¶r att rÃƒÂ¤dda Sverige och vÃƒÂ¥r utrikesminister. \nAtt hon egentligen blir blÃƒÂ¥st har hon dÃƒÂ¤remot ingen aning om. - Jag gick pÃƒÂ¥ det \nfullkomligt, sÃƒÂ¤ger hon i studion. I kvÃƒÂ¤llens BlÃƒÂ¥sningen passar vi ocksÃƒÂ¥ pÃƒÂ¥ att \nlura nÃƒÂ¥gra av landets frÃƒÂ¤msta komiker. David Batra fÃƒÂ¥r en annorlunda kvÃƒÂ¤ll nÃƒÂ¤r \nhan gÃƒÂ¥r pÃƒÂ¥ en restaurang med en mycket mÃƒÂ¤rklig och lite vÃƒÂ¤l pÃƒÂ¥trÃƒÂ¤ngande kock. \nJohan Glans fÃƒÂ¥r det ocksÃƒÂ¥ tufft nÃƒÂ¤r han blir lÃƒÂ¤mnad ensam i en felparkerad bil \noch plÃƒÂ¶tsligt inser att hans sÃƒÂ¤kerhetsbÃƒÂ¤lte lÃƒÂ¥st sig.\n\n\n\niCAP's releaser fÃƒÂ¥r spridas utanfÃƒÂ¶r SweTV om\nreleasen ÃƒÂ¤r ofÃƒÂ¶rÃƒÂ¤ndrad!\n\nGreets:\n\nwww.swetv.org - Svensk Tv PÃƒÂ¥ Internet\n\n[ REMAiN - LiPAN - GFSON - SweTV - RUViL - smecken16 ]\n\n\n                   www.swetv.org","torrent":{"xt":"urn:btih:a2fdf9cc0f0a04168009c35cc618ddf044f01e0f","amp;dn":"Blasningen.S09E06.SWEDiSH.PDTV.XviD-iCAP","amp;tr":["udp%3A%2F%2Ftracker.openbittorrent.com%3A80","udp%3A%2F%2Fopen.demonii.com%3A1337","udp%3A%2F%2Ftracker.coppersurfer.tk%3A6969","udp%3A%2F%2Fexodus.desync.com%3A6969"],"infoHash":"a2fdf9cc0f0a04168009c35cc618ddf044f01e0f","infoHashBuffer":{"type":"Buffer","data":[162,253,249,204,15,10,4,22,128,9,195,92,198,24,221,240,68,240,30,15]},"announce":[],"urlList":[]}}