{"title":"the.game.s01e02.hdtv.xvid-The Away Game.avi","uid":5413335,"size":183544156,"categoryP":"video","categoryS":"tv_shows","magnet":"?xt=urn:btih:cd0a591094f32328fc536cb3c52411e08be2139a&amp;dn=the.game.s01e02.hdtv.xvid-The+Away+Game.avi&amp;tr=udp%3A%2F%2Ftracker.openbittorrent.com%3A80&amp;tr=udp%3A%2F%2Fopen.demonii.com%3A1337&amp;tr=udp%3A%2F%2Ftracker.coppersurfer.tk%3A6969&amp;tr=udp%3A%2F%2Fexodus.desync.com%3A6969","seeders":0,"leechers":1,"uploader":"manic05","files":1,"time":1267820959,"description":"The Game Season 1 Episode 2","torrent":{"xt":"urn:btih:cd0a591094f32328fc536cb3c52411e08be2139a","amp;dn":"the.game.s01e02.hdtv.xvid-The+Away+Game.avi","amp;tr":["udp%3A%2F%2Ftracker.openbittorrent.com%3A80","udp%3A%2F%2Fopen.demonii.com%3A1337","udp%3A%2F%2Ftracker.coppersurfer.tk%3A6969","udp%3A%2F%2Fexodus.desync.com%3A6969"],"infoHash":"cd0a591094f32328fc536cb3c52411e08be2139a","infoHashBuffer":{"type":"Buffer","data":[205,10,89,16,148,243,35,40,252,83,108,179,197,36,17,224,139,226,19,154]},"announce":[],"urlList":[]}}