{"title":"angel.S03E09.dvdrip","uid":5367174,"size":365101056,"categoryP":"video","categoryS":"movies","magnet":"?xt=urn:btih:cd5396f365463bc9b0e37fa1434e7ead1f820938&amp;dn=angel.S03E09.dvdrip&amp;tr=udp%3A%2F%2Ftracker.openbittorrent.com%3A80&amp;tr=udp%3A%2F%2Fopen.demonii.com%3A1337&amp;tr=udp%3A%2F%2Ftracker.coppersurfer.tk%3A6969&amp;tr=udp%3A%2F%2Fexodus.desync.com%3A6969","seeders":0,"leechers":1,"uploader":"umj","files":-1,"time":1266301840,"description":"angel.S03E09.dvdrip","torrent":{"xt":"urn:btih:cd5396f365463bc9b0e37fa1434e7ead1f820938","amp;dn":"angel.S03E09.dvdrip","amp;tr":["udp%3A%2F%2Ftracker.openbittorrent.com%3A80","udp%3A%2F%2Fopen.demonii.com%3A1337","udp%3A%2F%2Ftracker.coppersurfer.tk%3A6969","udp%3A%2F%2Fexodus.desync.com%3A6969"],"infoHash":"cd5396f365463bc9b0e37fa1434e7ead1f820938","infoHashBuffer":{"type":"Buffer","data":[205,83,150,243,101,70,59,201,176,227,127,161,67,78,126,173,31,130,9,56]},"announce":[],"urlList":[]}}