{"title":"V.A. - Tranceparty Des 2009 by DJ Darkstar","uid":5200157,"size":121594253,"categoryP":"audio","categoryS":"music","magnet":"?xt=urn:btih:d42c98a49d15ee426130343af2dbee2aec2ed263&amp;dn=V.A.+-+Tranceparty+Des+2009+by+DJ+Darkstar&amp;tr=udp%3A%2F%2Ftracker.openbittorrent.com%3A80&amp;tr=udp%3A%2F%2Fopen.demonii.com%3A1337&amp;tr=udp%3A%2F%2Ftracker.coppersurfer.tk%3A6969&amp;tr=udp%3A%2F%2Fexodus.desync.com%3A6969","seeders":0,"leechers":1,"uploader":"Darkydark","files":15,"time":1260120959,"description":"*******************************************************************************\n                       Tranceparty Des 2009 by DJ Darkstar\n*******************************************************************************\n\n-------------------------------------------------------------------------------\n                              General Information\n-------------------------------------------------------------------------------\nType.................: Music\n\nTitle................: Tranceparty Des 2009 by DJ Darkstar\nArtist...............: V.A.\nAlbum................: Tranceparty Des 2009 by DJ Darkstar\nYear.................: 2009\nGenre................: Trance\nDuration.............: 01:17:17\nNumber of Songs......: 12\n\nAudio Format.........: MP3\nEncoder..............: LAME\nBitrate..............: 192 (VBR)\nHz...................: 44,100\nChannels.............: Stereo\n\n\n-------------------------------------------------------------------------------\n                                 Release Notes\n-------------------------------------------------------------------------------\n              Tracklist Tranceparty Des 2009 by DJ Darkstar\n--------------------------------------------------------------------------------\n\n01 - DJ Aligator Feat. Heidi Degn - Shine 2009 (Crapman Remix Edit)\n02 - Austin Leeds Feat Steve Bertrand - Staring At The Sun (Jonas Stenberg \nRemix)\n03 - Above &amp; Beyond - Anjunabeach (Jerome Isma-Ae Remix)\n04 - Solarstone &amp; Alucard - Later Summer Fields (Ferry Corsten Remix)\n05 - Costa - Be with You (Original Mix)\n06 - Ron Van Den Beuken - Timeless 2009 (RAM &amp; Gordon Coutts Remix)\n07 - Sneijder - Warsaw (Original Mix)\n08 - Midway - What If\n09 - Dodo Basnak - No One Should Ever (Original Mix)\n10 - Midway - Amazon (Ferry Tayle &amp; Stephan R 2009 Universal Language Remix)\n11 - Taleamus - Far Away (Original Mix)\n12 - Solis - Empire\n\nENJOY!!!!!  AND PLAY IT LOUD","torrent":{"xt":"urn:btih:d42c98a49d15ee426130343af2dbee2aec2ed263","amp;dn":"V.A.+-+Tranceparty+Des+2009+by+DJ+Darkstar","amp;tr":["udp%3A%2F%2Ftracker.openbittorrent.com%3A80","udp%3A%2F%2Fopen.demonii.com%3A1337","udp%3A%2F%2Ftracker.coppersurfer.tk%3A6969","udp%3A%2F%2Fexodus.desync.com%3A6969"],"infoHash":"d42c98a49d15ee426130343af2dbee2aec2ed263","infoHashBuffer":{"type":"Buffer","data":[212,44,152,164,157,21,238,66,97,48,52,58,242,219,238,42,236,46,210,99]},"announce":[],"urlList":[]}}