{"title":"Antonio &amp; Dan BrasilianTS","uid":5425571,"size":54617729,"categoryP":"porn","categoryS":"pictures","magnet":"?xt=urn:btih:d7ee491f44b59223a2ae8489616679be64f1a6bd&amp;dn=Antonio+%26+Dan+BrasilianTS&amp;tr=udp%3A%2F%2Ftracker.openbittorrent.com%3A80&amp;tr=udp%3A%2F%2Fopen.demonii.com%3A1337&amp;tr=udp%3A%2F%2Ftracker.coppersurfer.tk%3A6969&amp;tr=udp%3A%2F%2Fexodus.desync.com%3A6969","seeders":0,"leechers":0,"uploader":"bofie","files":-1,"time":1268242256,"description":"Antonio &amp; Dan BrasilianTS\n\n\n &lt;a href=&quot;\nhttp://bayimg.com/nAlbGAacc&quot; rel=&quot;nofollow&quot; target=&quot;_NEW&quot;&gt;\nhttp://bayimg.com/nAlbGAacc&lt;/a&gt;\n &lt;a href=&quot;\nhttp://bayimg.com/NALBHAaCC&quot; rel=&quot;nofollow&quot; target=&quot;_NEW&quot;&gt;\nhttp://bayimg.com/NALBHAaCC&lt;/a&gt;\n\n","torrent":{"xt":"urn:btih:d7ee491f44b59223a2ae8489616679be64f1a6bd","amp;dn":"Antonio+%26+Dan+BrasilianTS","amp;tr":["udp%3A%2F%2Ftracker.openbittorrent.com%3A80","udp%3A%2F%2Fopen.demonii.com%3A1337","udp%3A%2F%2Ftracker.coppersurfer.tk%3A6969","udp%3A%2F%2Fexodus.desync.com%3A6969"],"infoHash":"d7ee491f44b59223a2ae8489616679be64f1a6bd","infoHashBuffer":{"type":"Buffer","data":[215,238,73,31,68,181,146,35,162,174,132,137,97,102,121,190,100,241,166,189]},"announce":[],"urlList":[]}}