{"title":"Prem Rawat en Albuquerque, Nuevo MÃƒÂ©jico","uid":5338770,"size":381507000,"categoryP":"video","categoryS":"other","magnet":"?xt=urn:btih:edc35ab34091e5495a66048070f10404ede24577&amp;dn=Prem+Rawat+en+Albuquerque%2C+Nuevo+M%C3%83%C2%A9jico&amp;tr=udp%3A%2F%2Ftracker.openbittorrent.com%3A80&amp;tr=udp%3A%2F%2Fopen.demonii.com%3A1337&amp;tr=udp%3A%2F%2Ftracker.coppersurfer.tk%3A6969&amp;tr=udp%3A%2F%2Fexodus.desync.com%3A6969","seeders":0,"leechers":1,"uploader":"Juanbusca","files":1,"time":1265397954,"description":"Prem Rawat, tambiÃƒÂ©n conocido como Maharaji, habla en una conferencia en Albuquerque, el 11 de septiembre de 2009 acerca de la Paz","torrent":{"xt":"urn:btih:edc35ab34091e5495a66048070f10404ede24577","amp;dn":"Prem+Rawat+en+Albuquerque%2C+Nuevo+M%C3%83%C2%A9jico","amp;tr":["udp%3A%2F%2Ftracker.openbittorrent.com%3A80","udp%3A%2F%2Fopen.demonii.com%3A1337","udp%3A%2F%2Ftracker.coppersurfer.tk%3A6969","udp%3A%2F%2Fexodus.desync.com%3A6969"],"infoHash":"edc35ab34091e5495a66048070f10404ede24577","infoHashBuffer":{"type":"Buffer","data":[237,195,90,179,64,145,229,73,90,102,4,128,112,241,4,4,237,226,69,119]},"announce":[],"urlList":[]}}