{"title":"ParaÃƒÂ­ba - Vida E Morte De Um Bandido","uid":5429950,"size":734224384,"categoryP":"video","categoryS":"movies","magnet":"?xt=urn:btih:f875cb2cb0a1cef4ccf998a31b05f71e9474c849&amp;dn=Para%C3%83%C2%ADba+-+Vida+E+Morte+De+Um+Bandido&amp;tr=udp%3A%2F%2Ftracker.openbittorrent.com%3A80&amp;tr=udp%3A%2F%2Fopen.demonii.com%3A1337&amp;tr=udp%3A%2F%2Ftracker.coppersurfer.tk%3A6969&amp;tr=udp%3A%2F%2Fexodus.desync.com%3A6969","seeders":0,"leechers":2,"uploader":null,"files":1,"time":1268380891,"description":"ParaÃƒÂ­ba, Vida e Morte de um Bandido de Victor Lima.","torrent":{"xt":"urn:btih:f875cb2cb0a1cef4ccf998a31b05f71e9474c849","amp;dn":"Para%C3%83%C2%ADba+-+Vida+E+Morte+De+Um+Bandido","amp;tr":["udp%3A%2F%2Ftracker.openbittorrent.com%3A80","udp%3A%2F%2Fopen.demonii.com%3A1337","udp%3A%2F%2Ftracker.coppersurfer.tk%3A6969","udp%3A%2F%2Fexodus.desync.com%3A6969"],"infoHash":"f875cb2cb0a1cef4ccf998a31b05f71e9474c849","infoHashBuffer":{"type":"Buffer","data":[248,117,203,44,176,161,206,244,204,249,152,163,27,5,247,30,148,116,200,73]},"announce":[],"urlList":[]}}